{
  "lastUpdated": "2025-10-27T20:20:33.126Z",
  "top10": [
    {
      "code": "895ZTD5I",
      "count": 12,
      "xp": 6250,
      "questXP": 5050,
      "referralXP": 1200
    },
    {
      "code": "SHLPDWCL",
      "count": 25,
      "xp": 3250,
      "questXP": 750,
      "referralXP": 2500
    },
    {
      "code": "04S3AISY",
      "count": 23,
      "xp": 3050,
      "questXP": 750,
      "referralXP": 2300
    },
    {
      "code": "LOWB3J9Y",
      "count": 21,
      "xp": 2850,
      "questXP": 750,
      "referralXP": 2100
    },
    {
      "code": "06I9AWD1",
      "count": 15,
      "xp": 2350,
      "questXP": 850,
      "referralXP": 1500
    },
    {
      "code": "IBDYPD9A",
      "count": 10,
      "xp": 2150,
      "questXP": 1150,
      "referralXP": 1000
    },
    {
      "code": "BTOI1RGH",
      "count": 11,
      "xp": 1850,
      "questXP": 750,
      "referralXP": 1100
    },
    {
      "code": "NATWQQOL",
      "count": 0,
      "xp": 1800,
      "questXP": 1800,
      "referralXP": 0
    },
    {
      "code": "I8JORMO7",
      "count": 7,
      "xp": 1550,
      "questXP": 850,
      "referralXP": 700
    },
    {
      "code": "88Z7BBN0",
      "count": 6,
      "xp": 1350,
      "questXP": 750,
      "referralXP": 600
    }
  ],
  "totalUsers": 396,
  "updateInterval": 60
}